Metadata-Version: 2.1
Name: spam-yo-friends
Version: 0.0.1
Summary: A basic package that allows you to spam text!
Home-page: UNKNOWN
Author: Cxstin
Author-email: <dobrecostindragos@gmail.com>
License: UNKNOWN
Keywords: python,spam,spamming,message spamming,message spam
Platform: UNKNOWN
Classifier: Development Status :: 1 - Planning
Classifier: Intended Audience :: Developers
Classifier: Programming Language :: Python :: 3
Classifier: Operating System :: Unix
Classifier: Operating System :: MacOS :: MacOS X
Classifier: Operating System :: Microsoft :: Windows
